MANIFEST.in
README.txt
setup.cfg
setup.py
docs/HISTORY.txt
docs/INSTALL.txt
docs/LICENSE.GPL
docs/LICENSE.txt
sc/__init__.py
sc.paster.package.egg-info/PKG-INFO
sc.paster.package.egg-info/SOURCES.txt
sc.paster.package.egg-info/dependency_links.txt
sc.paster.package.egg-info/entry_points.txt
sc.paster.package.egg-info/namespace_packages.txt
sc.paster.package.egg-info/not-zip-safe
sc.paster.package.egg-info/requires.txt
sc.paster.package.egg-info/top_level.txt
sc/paster/__init__.py
sc/paster/package/__init__.py
sc/paster/package/portal_package.py
sc/paster/package/docs/portal_package.txt
sc/paster/package/templates/portal_package/MANIFEST.in_tmpl
sc/paster/package/templates/portal_package/README.txt_tmpl
sc/paster/package/templates/portal_package/bootstrap.py
sc/paster/package/templates/portal_package/setup.cfg_tmpl
sc/paster/package/templates/portal_package/setup.py_tmpl
sc/paster/package/templates/portal_package/test-plone-3.3.x.cfg_tmpl
sc/paster/package/templates/portal_package/test-plone-4.0.x.cfg_tmpl
sc/paster/package/templates/portal_package/test-plone-4.1.x.cfg_tmpl
sc/paster/package/templates/portal_package/+namespace_package+/__init__.py
sc/paster/package/templates/portal_package/+namespace_package+/+namespace_package2+/__init__.py
sc/paster/package/templates/portal_package/+namespace_package+/+namespace_package2+/+package+/README.txt_tmpl
sc/paster/package/templates/portal_package/+namespace_package+/+namespace_package2+/+package+/__init__.py_tmpl
sc/paster/package/templates/portal_package/+namespace_package+/+namespace_package2+/+package+/config.py_tmpl
sc/paster/package/templates/portal_package/+namespace_package+/+namespace_package2+/+package+/configure.zcml_tmpl
sc/paster/package/templates/portal_package/+namespace_package+/+namespace_package2+/+package+/dependencies.zcml_tmpl
sc/paster/package/templates/portal_package/+namespace_package+/+namespace_package2+/+package+/setuphandlers.py_tmpl
sc/paster/package/templates/portal_package/+namespace_package+/+namespace_package2+/+package+/version.txt_tmpl
sc/paster/package/templates/portal_package/+namespace_package+/+namespace_package2+/+package+/browser/__init__.py
sc/paster/package/templates/portal_package/+namespace_package+/+namespace_package2+/+package+/browser/configure.zcml_tmpl
