Metadata-Version: 1.0
Name: sc.paster.package
Version: 0.8
Summary: Simples Consultoria's skeleton for a package to be used in Plone.
Home-page: http://www.simplesconsultoria.com.br/
Author: Erico Andrei
Author-email: erico@simplesconsultoria.com.br
License: GPL
Keywords: web zope plone development simples_consultoria
Platform: UNKNOWN
Classifier: Programming Language :: Python
Classifier: Topic :: Software Development :: Libraries :: Python Modules
